COPYING
INSTALL
KNOWN_BUGS
MANIFEST.in
README.rst
THANKS
pysam.py
setup.cfg
setup.py
doc/Makefile
doc/api.rst
doc/conf.py
doc/developer.rst
doc/faq.rst
doc/glossary.rst
doc/index.rst
doc/make.bat
doc/release.rst
doc/usage.rst
htslib/bgzf.c
htslib/bgzip.c
htslib/config.h
htslib/faidx.c
htslib/hfile.c
htslib/hfile_internal.h
htslib/hfile_irods.c
htslib/hfile_net.c
htslib/hts.c
htslib/htsfile.c
htslib/kfunc.c
htslib/knetfile.c
htslib/kstring.c
htslib/regidx.c
htslib/sam.c
htslib/synced_bcf_reader.c
htslib/tabix.c
htslib/tbx.c
htslib/vcf.c
htslib/vcf_sweep.c
htslib/vcfutils.c
htslib/version.h
htslib/cram/cram.h
htslib/cram/cram_codecs.c
htslib/cram/cram_codecs.h
htslib/cram/cram_decode.c
htslib/cram/cram_decode.h
htslib/cram/cram_encode.c
htslib/cram/cram_encode.h
htslib/cram/cram_index.c
htslib/cram/cram_index.h
htslib/cram/cram_io.c
htslib/cram/cram_io.h
htslib/cram/cram_samtools.c
htslib/cram/cram_samtools.h
htslib/cram/cram_stats.c
htslib/cram/cram_stats.h
htslib/cram/cram_structs.h
htslib/cram/files.c
htslib/cram/mFILE.c
htslib/cram/mFILE.h
htslib/cram/md5.c
htslib/cram/md5.h
htslib/cram/misc.h
htslib/cram/open_trace_file.c
htslib/cram/open_trace_file.h
htslib/cram/os.h
htslib/cram/pooled_alloc.c
htslib/cram/pooled_alloc.h
htslib/cram/rANS_byte.h
htslib/cram/rANS_static.c
htslib/cram/rANS_static.h
htslib/cram/sam_header.c
htslib/cram/sam_header.h
htslib/cram/string_alloc.c
htslib/cram/string_alloc.h
htslib/cram/thread_pool.c
htslib/cram/thread_pool.h
htslib/cram/vlen.c
htslib/cram/vlen.h
htslib/cram/zfio.c
htslib/cram/zfio.h
htslib/htslib/bgzf.h
htslib/htslib/faidx.h
htslib/htslib/hfile.h
htslib/htslib/hts.h
htslib/htslib/hts_defs.h
htslib/htslib/kfunc.h
htslib/htslib/khash.h
htslib/htslib/khash_str2int.h
htslib/htslib/klist.h
htslib/htslib/knetfile.h
htslib/htslib/kseq.h
htslib/htslib/ksort.h
htslib/htslib/kstring.h
htslib/htslib/regidx.h
htslib/htslib/sam.h
htslib/htslib/synced_bcf_reader.h
htslib/htslib/tbx.h
htslib/htslib/vcf.h
htslib/htslib/vcf_sweep.h
pysam_arm_linux.egg-info/PKG-INFO
pysam_arm_linux.egg-info/SOURCES.txt
pysam_arm_linux.egg-info/dependency_links.txt
pysam_arm_linux.egg-info/not-zip-safe
pysam_arm_linux.egg-info/top_level.txt
