Metadata-Version: 1.1
Name: pysam-arm-linux
Version: 0.8.3
Summary: pysam for ARM Linux GNUroot Debian on Nvidia Shield Tablet [Tegra K1]
Home-page: https://github.com/pysam-developers/pysam
Author: Andreas Heger
Author-email: andreas.heger@gmail.com
License: MIT
Platform: ALL
Requires: cython (>=0.21)
